README.rst
setup.py
approx_eigen/__init__.py
approx_eigen/householder.py
approx_eigen/matrix_test.py
kr_numerical_analysis.egg-info/PKG-INFO
kr_numerical_analysis.egg-info/SOURCES.txt
kr_numerical_analysis.egg-info/dependency_links.txt
kr_numerical_analysis.egg-info/top_level.txt