Metadata-Version: 1.0
Name: kr-numerical-analysis
Version: 0.1
Summary: The methods for numerical analysis is based on the book of J.D. Faires and R.L. Burden: "Numerical Analysis".
Home-page: https://github.com/kingraijun/numerical_analysis.git
Author: Ruben A. Idoy, Jr.
Author-email: king.raijun@gmail.com
License: UNKNOWN
Keywords: numerical analysis
Platform: UNKNOWN
